osfloorprice.py
osfloorprice-1.1.dist-info/METADATA
osfloorprice-1.1.dist-info/WHEEL
osfloorprice-1.1.dist-info/top_level.txt
osfloorprice-1.1.dist-info/RECORD
