Metadata-Version: 2.1
Name: osfloorprice
Version: 1.1
Summary: Get floor prices from OpenSea
Home-page: UNKNOWN
Author: Sem Moolenschot
Author-email: sem@moolenschot.nl
License: MIT
Platform: UNKNOWN
Classifier: Programming Language :: Python :: 3
Classifier: License :: OSI Approved :: MIT License
Classifier: Operating System :: OS Independent
Requires-Dist: cloudscraper (==1.2.58)
